Workbook

Sheet Dashboard
A1: BARRO INDUSTRIES — GOVERNMENT & INSTITUTIONAL BIDDINGS TRACKER
A2: PhilGEPS & Private Institutional Bids | Updated: June 16, 2026 | All amounts in Philippine Peso (₱)
B4: TOTAL BIDS | D4: WON / COMPLETED | F4: ACTIVE / PENDING | H4: PROSPECTIVE | J4: WIN RATE
B5: =COUNTA('Biddings Detail'!A3:A200) | D5: =COUNTIF('Biddings Detail'!F3:F200,"Won / Completed") | F5: =COUNTIF('Biddings Detail'!F3:F200,"Active / Pending") | H5: =COUNTIF('Biddings Detail'!F3:F200,"Prospective") | J5: =IFERROR(COUNTIF('Biddings Detail'!F3:F200,"Won / Completed")/COUNTA('Biddings Detail'!A3:A200),"-")
B8: TOTAL WON / COMPLETED VALUE (ABC ₱) | F8: =SUMIF('Biddings Detail'!F3:F200,"Won / Completed",'Biddings Detail'!H3:H200)
B9: TOTAL ACTIVE / PENDING (ABC ₱) | F9: =SUMIF('Biddings Detail'!F3:F200,"Active / Pending",'Biddings Detail'!H3:H200)
B10: TOTAL PROSPECTIVE PIPELINE (ABC ₱) | F10: =SUMIF('Biddings Detail'!F3:F200,"Prospective",'Biddings Detail'!H3:H200)
B12: STATUS BREAKDOWN
B13: STATUS | E13: COUNT | F13: % SHARE | G13: ABC TOTAL (₱)
B14: Won / Completed | E14: =COUNTIF('Biddings Detail'!F3:F200,"Won / Completed") | F14: =IFERROR(E14/COUNTA('Biddings Detail'!A3:A200),"-") | G14: =SUMIF('Biddings Detail'!F3:F200,"Won / Completed",'Biddings Detail'!H3:H200)
B15: Active / Pending | E15: =COUNTIF('Biddings Detail'!F3:F200,"Active / Pending") | F15: =IFERROR(E15/COUNTA('Biddings Detail'!A3:A200),"-") | G15: =SUMIF('Biddings Detail'!F3:F200,"Active / Pending",'Biddings Detail'!H3:H200)
B16: Prospective | E16: =COUNTIF('Biddings Detail'!F3:F200,"Prospective") | F16: =IFERROR(E16/COUNTA('Biddings Detail'!A3:A200),"-") | G16: =SUMIF('Biddings Detail'!F3:F200,"Prospective",'Biddings Detail'!H3:H200)
B17: Lost / Failed | E17: =COUNTIF('Biddings Detail'!F3:F200,"Lost / Failed") | F17: =IFERROR(E17/COUNTA('Biddings Detail'!A3:A200),"-") | G17: =SUMIF('Biddings Detail'!F3:F200,"Lost / Failed",'Biddings Detail'!H3:H200)
B18: Disqualified | E18: =COUNTIF('Biddings Detail'!F3:F200,"Disqualified") | F18: =IFERROR(E18/COUNTA('Biddings Detail'!A3:A200),"-") | G18: =SUMIF('Biddings Detail'!F3:F200,"Disqualified",'Biddings Detail'!H3:H200)
B21: AGENCY / CLIENT BREAKDOWN
B22: AGENCY / CLIENT | F22: BIDS | G22: STATUS | H22: ABC TOTAL (₱)
B23: DMMMSU | F23: =COUNTIF('Biddings Detail'!A3:A200,"DMMMSU") | H23: =SUMIF('Biddings Detail'!A3:A200,"DMMMSU",'Biddings Detail'!H3:H200)
B24: ISPSC | F24: =COUNTIF('Biddings Detail'!A3:A200,"ISPSC") | H24: =SUMIF('Biddings Detail'!A3:A200,"ISPSC",'Biddings Detail'!H3:H200)
B25: DepEd | F25: =COUNTIF('Biddings Detail'!A3:A200,"DepEd") | H25: =SUMIF('Biddings Detail'!A3:A200,"DepEd",'Biddings Detail'!H3:H200)
B26: ITRMC | F26: =COUNTIF('Biddings Detail'!A3:A200,"ITRMC") | H26: =SUMIF('Biddings Detail'!A3:A200,"ITRMC",'Biddings Detail'!H3:H200)
B27: BSU | F27: =COUNTIF('Biddings Detail'!A3:A200,"BSU") | H27: =SUMIF('Biddings Detail'!A3:A200,"BSU",'Biddings Detail'!H3:H200)
B28: Bethany Hospital | F28: =COUNTIF('Biddings Detail'!A3:A200,"Bethany Hospital") | H28: =SUMIF('Biddings Detail'!A3:A200,"Bethany Hospital",'Biddings Detail'!H3:H200)
B29: Candelaria Dist. Hospital | F29: =COUNTIF('Biddings Detail'!A3:A200,"Candelaria Dist. Hospital") | H29: =SUMIF('Biddings Detail'!A3:A200,"Candelaria Dist. Hospital",'Biddings Detail'!H3:H200)
B30: Kings College | F30: =COUNTIF('Biddings Detail'!A3:A200,"Kings College") | H30: =SUMIF('Biddings Detail'!A3:A200,"Kings College",'Biddings Detail'!H3:H200)
B31: El Cielito Hotel | F31: =COUNTIF('Biddings Detail'!A3:A200,"El Cielito Hotel") | H31: =SUMIF('Biddings Detail'!A3:A200,"El Cielito Hotel",'Biddings Detail'!H3:H200)
B32: Chateau De Maisons | F32: =COUNTIF('Biddings Detail'!A3:A200,"Chateau De Maisons") | H32: =SUMIF('Biddings Detail'!A3:A200,"Chateau De Maisons",'Biddings Detail'!H3:H200)
B33: Lorma Colleges | F33: =COUNTIF('Biddings Detail'!A3:A200,"Lorma Colleges") | H33: =SUMIF('Biddings Detail'!A3:A200,"Lorma Colleges",'Biddings Detail'!H3:H200)
B34: J&V | F34: =COUNTIF('Biddings Detail'!A3:A200,"J&V") | H34: =SUMIF('Biddings Detail'!A3:A200,"J&V",'Biddings Detail'!H3:H200)
B35: BSBT | F35: =COUNTIF('Biddings Detail'!A3:A200,"BSBT") | H35: =SUMIF('Biddings Detail'!A3:A200,"BSBT",'Biddings Detail'!H3:H200)
B36: Ridgewood Hotel | F36: =COUNTIF('Biddings Detail'!A3:A200,"Ridgewood Hotel") | H36: =SUMIF('Biddings Detail'!A3:A200,"Ridgewood Hotel",'Biddings Detail'!H3:H200)
B37: Chimichanga Restaurant | F37: =COUNTIF('Biddings Detail'!A3:A200,"Chimichanga Restaurant") | H37: =SUMIF('Biddings Detail'!A3:A200,"Chimichanga Restaurant",'Biddings Detail'!H3:H200)
B38: Jackie Red Ausa | F38: =COUNTIF('Biddings Detail'!A3:A200,"Jackie Red Ausa") | H38: =SUMIF('Biddings Detail'!A3:A200,"Jackie Red Ausa",'Biddings Detail'!H3:H200)

Sheet Biddings Detail
A1: BARRO INDUSTRIES — GOVERNMENT & INSTITUTIONAL BIDDINGS DETAIL
A2: # | B2: Agency / Client | C2: Location | D2: Category / Lot | E2: Item Description | F2: Year | G2: Status | H2: Outcome | I2: ABC / Contract Amount (₱) | J2: Bid Price Submitted (₱) | K2: Documents on File | L2: Remarks / Notes | M2: Date Submitted | N2: Last Updated
A3: 1 | B3: DMMMSU | C3: San Fernando, La Union | D3: Kitchen Equipment | E3: Supply & Fabrication of Kitchen Equipment (various lots) | F3: 2024 | G3: Won / Completed | H3: WON | I3: 13494887 | J3: 13494887 | K3: Project Portfolio DOCX, Completion Docs | L3: Kitchen equipment portfolio; completed and delivered
A4: 2 | B4: DMMMSU | C4: San Fernando, La Union | D4: Appliances | E4: Supply of Appliances (AC units, refrigerators, etc.) | F4: 2024 | G4: Won / Completed | H4: WON | I4: 1709634 | J4: 1709634 | K4: Project Portfolio DOCX | L4: Part of same portfolio; delivered
A5: 3 | B5: ISPSC | C5: Ilocos Sur | D5: Machinery & Equipment | E5: Supply of Machinery & Equipment (various kitchen/lab items) | F5: 2025 | G5: Won / Completed | H5: WON | I5: 5157746.3 | J5: 5100000 | K5: Notice of Award, MOA, Job Order, NTP, PhilGEPS Docs | L5: ABC ₱5,157,746.28; submitted ₱5,100,000; full PhilGEPS docs on file; MOA + NTP signed
A6: 4 | B6: ISPSC | C6: Ilocos Sur | D6: Kitchen Fixtures | E6: Supply & Installation of Kitchen Fixtures and Equipment | F6: 2025 | G6: Active / Pending | H6: Pending | I6: 5157746.3 | J6: 5100000 | K6: Bid Documents + Technical Specs | L6: Bid submitted; awaiting award; same ABC as machinery lot
A7: 5 | B7: DepEd | C7: Baguio City | D7: Laboratory Equipment | E7: Supply of School Laboratory & Science Equipment | F7: 2024 | G7: Won / Completed | H7: WON | I7: 1196487 | J7: 1196487 | K7: Market Survey, PO-3277 (Narciso), PO Signed (DepEd) | L7: Two signed POs on file; purchase order awarded Nov 18, 2024
A8: 6 | B8: ITRMC | C8: La Union | D8: Kitchen Equipment | E8: Supply & Fabrication of Kitchen Equipment | F8: 2025 | G8: Won / Completed | H8: WON | I8: 998000 | J8: 998000 | K8: Multiple Quotations, PO 2026-01-0040, Canvas Forms, Job Order, Site Photos | L8: PO 2026-01-0040 issued Jan 2026; site photos Dec 2025; finalized
A9: 7 | B9: BSU | C9: La Trinidad, Benguet | D9: Equipment Supply | E9: Supply of Various Equipment (RFQ) | F9: 2026 | G9: Active / Pending | H9: Pending | I9: 106000 | J9: 106000 | K9: RFQ Quotation 2026-01-26 | L9: RFQ submitted Jan 26, 2026; awaiting award
A10: 8 | B10: Bethany Hospital | C10: San Fernando, La Union | D10: Kitchen & Systems | E10: Hospital Kitchen Equipment, Exhaust, Trolleys, and Site Works | F10: 2024 | G10: Won / Completed | H10: WON | I10: 1656300 | J10: 1656300 | K10: Contract, Billing Invoice, Final Billing, Multiple Quotations, Job Order, Site Photos | L10: Completed multi-phase project; final billing issued
A11: 9 | B11: Candelaria Dist. Hospital | C11: Zambales | D11: Kitchen Equipment | E11: Hospital Kitchen Equipment & Fabrication (3 Sections) | F11: 2025 | G11: Active / Pending | H11: Pending | I11: 2292000 | J11: 2292000 | K11: Revised Quotation Parts 1 & 2 (DOCX + PDF) | L11: Proposal submitted; 3 sections; awaiting award
A12: 10 | B12: Kings College | C12: La Trinidad, Benguet | D12: HVAC / Hood Systems | E12: Fabrication & Repair of Hood and Duct System | F12: 2024 | G12: Active / Pending | H12: Pending | I12: 199000 | J12: 199000 | K12: Quotation (DOCX, PDF) | L12: Quotation submitted; awaiting decision
A13: 11 | B13: El Cielito Hotel | C13: Baguio City | D13: Ventilation System | E13: Supply & Installation of Exhaust and Fresh Air System | F13: 2024 | G13: Prospective | H13: N/A | I13: 1428800 | J13: — | K13: Price Quotation (DOCX) | L13: Large ventilation project; quotation issued; awaiting PO
A14: 12 | B14: Chateau De Maisons | C14: Baguio City | D14: Kitchen Design | E14: Kitchen Equipment Layout and Design | F14: 2025 | G14: Prospective | H14: N/A | I14: TBD | J14: — | K14: AutoCAD DWG Plan | L14: Design phase; no bid submitted yet
A15: 13 | B15: Lorma Colleges | C15: San Fernando, La Union | D15: Kitchen Equipment | E15: Kitchen Equipment Supply (Preliminary Quotation) | F15: 2025 | G15: Prospective | H15: N/A | I15: TBD | J15: — | K15: Preliminary Quotation (XLSX) | L15: Preliminary stage; formal bid not yet submitted
A16: 14 | B16: J&V | C16: Unknown | D16: Kitchen Design | E16: Kitchen Layout Design | F16: 2025 | G16: Prospective | H16: N/A | I16: TBD | J16: — | K16: AutoCAD DWG + Reference Image | L16: Design only; no formal bid
A17: 15 | B17: BSBT | C17: Baguio City | D17: Kitchen & Bar Setup | E17: Kitchen & Bar Fabrication (MOA Signed) | F17: 2025 | G17: Active / Pending | H17: Pending | I17: TBD | J17: — | K17: MOA, Kitchen Plans, AutoCAD DWG, Design Files | L17: MOA signed; negotiated project, not PhilGEPS
A18: 16 | B18: Ridgewood Hotel | C18: Baguio City | D18: Kitchen Equipment | E18: Kitchen Equipment Supply + Preventive Maintenance | F18: 2025 | G18: Active / Pending | H18: Pending | I18: 313900 | J18: 313900 | K18: Multiple Quotations, Job Order (Final), PM Contract | L18: Repeat client; PM contract active ₱24,000/yr
A19: 17 | B19: Chimichanga Restaurant | C19: Baguio City | D19: Kitchen Equipment | E19: Fabrication of Kitchen Equipment | F19: 2025 | G19: Prospective | H19: N/A | I19: 754600 | J19: 754600 | K19: Quotation (DOCX + PDF, with/without price versions) | L19: Private sector; large kitchen setup quotation
A20: 18 | B20: Jackie Red Ausa | C20: Itogon, Benguet | D20: Kitchen Setup | E20: Fabrication, Supply & Installation of Full Kitchen Setup | F20: 2025 | G20: Prospective | H20: N/A | I20: 1246900 | J20: 1246900 | K20: Price Quotation (DOCX, PDF) | L20: Full kitchen fabrication quotation

Sheet PhilGEPS Checklist
A1: PHILGEPS BIDDING DOCUMENT CHECKLIST
A2: Reference: RA 9184 / GPPB Guidelines | Mark status per active bid
B3: ITEM # | C3: DOCUMENT REQUIRED | D3: STATUS | E3: DATE SUBMITTED / PREPARED | F3: REMARKS
B4: 1 | C4: Letter of Intent (LOI) | D4: ☐ On File ☐ Needed ☐ N/A
B5: 2 | C5: PhilGEPS Registration Certificate | D5: ☐ On File ☐ Needed ☐ N/A
B6: 3 | C6: Mayor's / Business Permit | D6: ☐ On File ☐ Needed ☐ N/A
B7: 4 | C7: Tax Clearance Certificate (BIR) | D7: ☐ On File ☐ Needed ☐ N/A
B8: 5 | C8: Income / Business Tax Return | D8: ☐ On File ☐ Needed ☐ N/A
B9: 6 | C9: Audited Financial Statements (latest year) | D9: ☐ On File ☐ Needed ☐ N/A
B10: 7 | C10: PCAB License (if works contract) | D10: ☐ On File ☐ Needed ☐ N/A
B11: 8 | C11: Omnibus Sworn Statement | D11: ☐ On File ☐ Needed ☐ N/A
B12: 9 | C12: Technical Specifications / Brochures | D12: ☐ On File ☐ Needed ☐ N/A
B13: 10 | C13: Statement of All Ongoing Government Contracts | D13: ☐ On File ☐ Needed ☐ N/A
B14: 11 | C14: Certificate of Completed Similar Contracts | D14: ☐ On File ☐ Needed ☐ N/A
B15: 12 | C15: Net Financial Contracting Capacity (NFCC) | D15: ☐ On File ☐ Needed ☐ N/A
... B21: 18 | C21: Price / Bill of Quantities | D21: ☐ On File ☐ Needed ☐ N/A
